[
  { "input": "I am extremely delighted", "output": "Happy" },
  { "input": "I feel really down", "output": "Sad" },
  { "input": "LOL, that's hilarious", "output": "Happy" },
  { "input": "I am utterly dissatisfied", "output": "Sad" },
  { "input": "I am absolutely furious", "output": "Angry" },
  { "input": "You drive me insane", "output": "Angry" },
  { "input": "My day has been uneventful", "output": "Neutral" },
  { "input": "This news makes me ecstatic", "output": "Happy" },
  { "input": "The outcome is devastating", "output": "Sad" },
  { "input": "I am chuckling uncontrollably", "output": "Happy" },
  { "input": "The situation is disheartening", "output": "Sad" },
  { "input": "I am seething with rage", "output": "Angry" },
  { "input": "You make me livid with your lies", "output": "Angry" },
  { "input": "I have no particular opinion", "output": "Neutral" },
  { "input": "I am thrilled beyond words", "output": "Happy" },
  { "input": "The news brings tears to my eyes", "output": "Sad" },
  { "input": "I am overjoyed with excitement", "output": "Happy" },
  { "input": "The service is absolutely terrible", "output": "Sad" },
  { "input": "I am boiling with anger", "output": "Angry" },
  { "input": "You make me infuriated with your behavior", "output": "Angry" },
  { "input": "I am indifferent to this matter", "output": "Neutral" },
  { "input": "I feel blissful and content", "output": "Happy" },
  { "input": "The news is profoundly saddening", "output": "Sad" },
  { "input": "I am beaming with joy", "output": "Happy" },
  { "input": "The outcome is underwhelming", "output": "Sad" },
  { "input": "I am boiling with rage", "output": "Angry" },
  { "input": "You make me furious with your constant lies", "output": "Angry" },
  { "input": "I have no opinion on this topic", "output": "Neutral" },
  { "input": "I feel exhilarated by the good news", "output": "Happy" },
  { "input": "The movie evokes a sense of melancholy", "output": "Sad" },
  { "input": "I am ecstatic about the upcoming event", "output": "Happy" }
]